siren_dsl/__init__.py
siren_dsl/config.py
siren_dsl/fable_modules/.gitignore
siren_dsl/fable_modules/fable_library/__init__.py
siren_dsl/fable_modules/fable_library/array_.py
siren_dsl/fable_modules/fable_library/async_.py
siren_dsl/fable_modules/fable_library/async_builder.py
siren_dsl/fable_modules/fable_library/big_int.py
siren_dsl/fable_modules/fable_library/bit_converter.py
siren_dsl/fable_modules/fable_library/boolean.py
siren_dsl/fable_modules/fable_library/char.py
siren_dsl/fable_modules/fable_library/choice.py
siren_dsl/fable_modules/fable_library/date.py
siren_dsl/fable_modules/fable_library/date_offset.py
siren_dsl/fable_modules/fable_library/decimal_.py
siren_dsl/fable_modules/fable_library/diagnostics.py
siren_dsl/fable_modules/fable_library/double.py
siren_dsl/fable_modules/fable_library/encoding.py
siren_dsl/fable_modules/fable_library/event.py
siren_dsl/fable_modules/fable_library/file.py
siren_dsl/fable_modules/fable_library/fsharp_collections.py
siren_dsl/fable_modules/fable_library/fsharp_core.py
siren_dsl/fable_modules/fable_library/global_.py
siren_dsl/fable_modules/fable_library/guid.py
siren_dsl/fable_modules/fable_library/int32.py
siren_dsl/fable_modules/fable_library/list.py
siren_dsl/fable_modules/fable_library/long.py
siren_dsl/fable_modules/fable_library/mailbox_processor.py
siren_dsl/fable_modules/fable_library/map.py
siren_dsl/fable_modules/fable_library/map_util.py
siren_dsl/fable_modules/fable_library/mutable_map.py
siren_dsl/fable_modules/fable_library/mutable_set.py
siren_dsl/fable_modules/fable_library/native.py
siren_dsl/fable_modules/fable_library/numeric.py
siren_dsl/fable_modules/fable_library/observable.py
siren_dsl/fable_modules/fable_library/option.py
siren_dsl/fable_modules/fable_library/path.py
siren_dsl/fable_modules/fable_library/range.py
siren_dsl/fable_modules/fable_library/reflection.py
siren_dsl/fable_modules/fable_library/reg_exp.py
siren_dsl/fable_modules/fable_library/resize_array.py
siren_dsl-0.3.2.dist-info/METADATA
siren_dsl-0.3.2.dist-info/WHEEL
siren_dsl-0.3.2.dist-info/RECORD
