Metadata-Version: 2.1
Name: siren-dsl
Version: 0.3.2
Summary: A simple dsl for creating mermaid graphs!
Home-page: https://github.com/Freymaurer/Siren
Keywords: mermaid,dsl,fable,graphs
Author: Kevin Frey
Author-email: freymaurer@gmx.de
Requires-Python: >=3.11,<4.0
Classifier: Programming Language :: Python :: 3
Classifier: Programming Language :: Python :: 3.11
Classifier: Programming Language :: Python :: 3.12
Requires-Dist: fable-library (>=0.9.0,<0.10.0)
Project-URL: Repository, https://github.com/Freymaurer/Siren
